LICENSE
MANIFEST.in
README.md
dev-requirements.txt
requirements.txt
setup.py
gnu_health_fhir/VERSION
gnu_health_fhir/__init__.py
gnu_health_fhir.egg-info/PKG-INFO
gnu_health_fhir.egg-info/SOURCES.txt
gnu_health_fhir.egg-info/dependency_links.txt
gnu_health_fhir.egg-info/not-zip-safe
gnu_health_fhir.egg-info/requires.txt
gnu_health_fhir.egg-info/top_level.txt