Metadata-Version: 2.1
Name: gnu-health-fhir
Version: 2.0.0
Summary: Provides FHIR interface to GNU Health.
Home-page: https://github.com/teffalump/gnu_health_fhir
Author: teffalump
Author-email: chris@teffalump.com
License: UNKNOWN
Platform: UNKNOWN
Classifier: Development Status :: 2 - Pre-Alpha
Classifier: Programming Language :: Python
Classifier: Programming Language :: Python :: 3
Classifier: Intended Audience :: Developers
Classifier: License :: OSI Approved :: GNU General Public License v3 or later (GPLv3+)
Classifier: Operating System :: OS Independent
